README.md
setup.cfg
setup.py
eis/__init__.py
eis/document/__init__.py
eis/document/api_client.py
eis/document/configuration.py
eis/document/exceptions.py
eis/document/model_utils.py
eis/document/rest.py
eis/document/api/__init__.py
eis/document/api/default_api.py
eis/document/api/document_templates_api.py
eis/document/api/documents_api.py
eis/document/api/docx_templates_api.py
eis/document/api/layouts_api.py
eis/document/api/product_documents_api.py
eis/document/api/search_keywords_api.py
eis/document/api/searchable_document_owners_api.py
eis/document/api/searchable_documents_api.py
eis/document/apis/__init__.py
eis/document/model/__init__.py
eis/document/model/create_doc_template_request_dto.py
eis/document/model/create_doc_template_response_class.py
eis/document/model/create_document_request_dto.py
eis/document/model/create_document_sync_response_class.py
eis/document/model/create_html_template_dto.py
eis/document/model/create_layout_request_dto.py
eis/document/model/create_layout_response_class.py
eis/document/model/create_presigned_post_request_dto.py
eis/document/model/create_presigned_post_response_class.py
eis/document/model/create_qr_bill_document_request_dto.py
eis/document/model/delete_layout_request_dto.py
eis/document/model/delete_product_document_request_dto.py
eis/document/model/delete_request_dto.py
eis/document/model/delete_response_class.py
eis/document/model/doc_template_class.py
eis/document/model/document_class.py
eis/document/model/docx_template_class.py
eis/document/model/download_document_request_dto.py
eis/document/model/export_document_request_dto.py
eis/document/model/export_document_response_class.py
eis/document/model/get_doc_template_request_dto.py
eis/document/model/get_doc_template_response_class.py
eis/document/model/get_document_download_url_response_class.py
eis/document/model/get_docx_template_download_url_response_class.py
eis/document/model/get_docx_template_response_class.py
eis/document/model/get_layout_request_dto.py
eis_documents.egg-info/PKG-INFO
eis_documents.egg-info/SOURCES.txt
eis_documents.egg-info/dependency_links.txt
eis_documents.egg-info/requires.txt
eis_documents.egg-info/top_level.txt
