Metadata-Version: 2.1
Name: eis-documents
Version: 1.40.0
Summary: EMIL DocumentService
Home-page: UNKNOWN
Author: Contact us
Author-email: kontakt@emil.de
License: UNKNOWN
Keywords: OpenAPI,OpenAPI-Generator,EMIL DocumentService
Platform: UNKNOWN
Requires-Python: >=3.6
